LICENSE
MANIFEST.in
README.md
setup.py
config/apache.conf
config/haproxy.conf
config/nginx.conf
config/php-fpm.conf
config/rdiff-backup.conf
config/redis.conf
config/sphinx.conf
config/zabbix/apache.conf
config/zabbix/haproxy.conf
config/zabbix/nginx.conf
config/zabbix/php-fpm.conf
config/zabbix/rdiff-backup.conf
templates/template_app_apache.xml
templates/template_app_haproxy.xml
zems/__init__.py
zems/apache.py
zems/check.py
zems/commands.py
zems/haproxy.py
zems/main.py
zems/nginx.py
zems/phpfpm.py
zems/rdiffbackup.py
zems/redis.py
zems/sphinx.py
zems.egg-info/PKG-INFO
zems.egg-info/SOURCES.txt
zems.egg-info/dependency_links.txt
zems.egg-info/entry_points.txt
zems.egg-info/requires.txt
zems.egg-info/top_level.txt
zems/lib/__init__.py
zems/lib/cache.py
zems/lib/fcgiconnector.py
zems/lib/flup_fcgi_client.py
zems/lib/mysqlconnector.py
zems/lib/socketconnector.py
zems/lib/urlconnector.py
zems/lib/utils.py