Metadata-Version: 1.0
Name: zems
Version: 0.0.7
Summary: ZEMS (Zabbix Extended Monitoring Scripts) is a tool to retrieve all sorts of metrics from applications and deliver it to Zabbix in a generic way.
Home-page: https://github.com/marijngiesen/zabbix-ems
Author: Marijn Giesen
Author-email: marijn@studio-donder.nl
License: GPL
Platform: UNKNOWN
